LICENSE
MANIFEST.in
README.md
requirements.txt
setup.cfg
setup.py
athena/__init__.py
athena/connection.py
athena/magic.py
jupyter_athena_sql.egg-info/PKG-INFO
jupyter_athena_sql.egg-info/SOURCES.txt
jupyter_athena_sql.egg-info/dependency_links.txt
jupyter_athena_sql.egg-info/requires.txt
jupyter_athena_sql.egg-info/top_level.txt