Metadata-Version: 1.1
Name: jupyter-athena-sql
Version: 0.0.4
Summary: run SQL queries on AWS Athena from jupyter notebooks
Home-page: https://github.com/finklabs/jupyter-athena-sql
Author: finklabs
Author-email: mark@finklabs.de
License: MIT
Platform: UNKNOWN
Classifier: Natural Language :: English
Classifier: Intended Audience :: Developers
Classifier: Environment :: Console
Classifier: License :: OSI Approved :: MIT License
Classifier: Programming Language :: Python :: 2.7
Classifier: Programming Language :: Python :: 3.6
